cloudflare_ddns/cli.py
cloudflare_ddns/cloudflareddns.py
cloudflare_ddns/gen_settings.py
cloudflare_ddns/internals.py
cloudflare_ddns/verify.py
simple_cloudflare_ddns-4.0.0.dist-info/LICENSE
simple_cloudflare_ddns-4.0.0.dist-info/METADATA
simple_cloudflare_ddns-4.0.0.dist-info/WHEEL
simple_cloudflare_ddns-4.0.0.dist-info/entry_points.txt
simple_cloudflare_ddns-4.0.0.dist-info/top_level.txt
simple_cloudflare_ddns-4.0.0.dist-info/RECORD
