Metadata-Version: 2.1
Name: simple-cloudflare-ddns
Version: 4.0.0
Summary: A super simple cli tool to update dns records
Home-page: https://github.com/advaithm/cloudflare-DDNS
Author: nullrequest
Author-email: advaith.madhukar@gmail.com
License: GPLv3
Platform: UNKNOWN
Classifier: Development Status :: 5 - Production/Stable
Classifier: Environment :: Console
Classifier: Intended Audience :: Customer Service
Classifier: License :: OSI Approved :: GNU General Public License v3 (GPLv3)
Classifier: Natural Language :: English
Classifier: Operating System :: POSIX :: Linux
Classifier: Programming Language :: Python :: 3 :: Only
Classifier: Programming Language :: Python :: 3.8
Classifier: Programming Language :: Python :: 3.9
Requires-Dist: requests
Requires-Dist: pyyaml
Requires-Dist: sockets
